codedipcalculator/__init__.py
codedipcalculator-0.1.dist-info/LICENCE.txt
codedipcalculator-0.1.dist-info/METADATA
codedipcalculator-0.1.dist-info/WHEEL
codedipcalculator-0.1.dist-info/top_level.txt
codedipcalculator-0.1.dist-info/RECORD
