Metadata-Version: 2.1
Name: codedipcalculator
Version: 0.1
Summary: This is Basic Calculator
Home-page: UNKNOWN
Author: Dipchandra
Author-email: dipchandra.nit@gmail.com
License: UNKNOWN
Platform: UNKNOWN
Classifier: Programming Language :: Python :: 3
Classifier: License :: OSI Approved :: MIT License
Classifier: Operating System :: OS Independent
License-File: LICENCE.txt
